__init__.py
main.py
make_datasetfolder-0.0.1.dist-info/LICENSE
make_datasetfolder-0.0.1.dist-info/METADATA
make_datasetfolder-0.0.1.dist-info/WHEEL
make_datasetfolder-0.0.1.dist-info/entry_points.txt
make_datasetfolder-0.0.1.dist-info/top_level.txt
make_datasetfolder-0.0.1.dist-info/RECORD
