Metadata-Version: 2.1
Name: make-datasetfolder
Version: 0.0.1
Summary: A utility to create a PyTorch DatasetFolder from any .csv or .tsv file with file path and class data.
Home-page: https://github.com/eczy/make-datasetfolder
Author: Evan Czyzycki
Author-email: eczy3826@gmail.com
License: UNKNOWN
Platform: UNKNOWN
Requires-Python: >=3.5
